[
    {
        "src": "https://images.unsplash.com/photo-1506905925346-21bda4d32df4?w=600",
        "title": "Mountain Vista",
        "category": "landscape"
    },
    {
        "src": "https://images.unsplash.com/photo-1470071459604-3b5ec3a7fe05?w=600",
        "title": "Foggy Forest",
        "category": "landscape"
    },
    {
        "src": "https://images.unsplash.com/photo-1441974231531-c6227db76b6e?w=600",
        "title": "Sunlit Path",
        "category": "nature"
    },
    {
        "src": "https://images.unsplash.com/photo-1469474968028-56623f02e42e?w=600",
        "title": "Nature's Beauty",
        "category": "nature"
    },
    {
        "src": "https://images.unsplash.com/photo-1447752875215-b2761acb3c5d?w=600",
        "title": "Golden Hour",
        "category": "landscape"
    },
    {
        "src": "https://images.unsplash.com/photo-1433086966358-54859d0ed716?w=600",
        "title": "Waterfall",
        "category": "nature"
    }
]